atlassian_marketplace_python_client/__init__.py
atlassian_marketplace_python_client/atlassian_marketplace_api.py
atlassian_marketplace_python_client/settings.py
atlassian_marketplace_python_client-0.3.1.dist-info/LICENSE
atlassian_marketplace_python_client-0.3.1.dist-info/METADATA
atlassian_marketplace_python_client-0.3.1.dist-info/WHEEL
atlassian_marketplace_python_client-0.3.1.dist-info/top_level.txt
atlassian_marketplace_python_client-0.3.1.dist-info/RECORD
