Metadata-Version: 2.1
Name: atlassian-marketplace-python-client
Version: 0.3.1
Summary: The Python Client for the Atlassian Marketplace
Home-page: https://github.com/seibert-media/atlassian_marketplace_python_client
Author: Jean Petry
Author-email: jpetry@seibert-media.net
License: UNKNOWN
Platform: UNKNOWN
Classifier: Programming Language :: Python :: 3
Classifier: License :: OSI Approved :: MIT License
Classifier: Operating System :: OS Independent
Requires-Python: >=3.0
License-File: LICENSE
Requires-Dist: requests (>=2.20.0)
